mfire/VERSION
mfire/__init__.py
mfire/composite/__init__.py
mfire/composite/aggregation.py
mfire/composite/base.py
mfire/composite/component.py
mfire/composite/event.py
mfire/composite/field.py
mfire/composite/geo.py
mfire/composite/level.py
mfire/composite/operator.py
mfire/composite/period.py
mfire/composite/production.py
mfire/composite/serialized_types.py
mfire/configuration/__init__.py
mfire/configuration/component.py
mfire/configuration/geo.py
mfire/configuration/period.py
mfire/configuration/processor.py
mfire/configuration/production.py
mfire/configuration/rules.py
mfire/data/__init__.py
mfire/data/cumul.py
mfire/data/data_preprocessor.py
mfire/data/downscale.py
mfire/data/grib_reader.py
mfire/data/instant.py
mfire/data/prepare_stack.py
mfire/data/run_info.py
mfire/locale/en/compass.json
mfire/locale/en/date.json
mfire/locale/en/period.csv
mfire/locale/en/synonyms.json
mfire/locale/en/wwmf_labels.csv
mfire/locale/en/LC_MESSAGES/mfire.mo
mfire/locale/en/risk/ME.json
mfire/locale/en/risk/monozone.csv
mfire/locale/en/risk/multizone.json
mfire/locale/en/risk/rain.json
mfire/locale/en/risk/rep_value.json
mfire/locale/en/risk/rep_value_altitude.json
mfire/locale/en/risk/rep_value_lpn.json
mfire/locale/en/risk/snow.json
mfire/locale/en/synthesis/nebulosity_following_labels.csv
mfire/locale/en/synthesis/temperature.json
mfire/locale/en/synthesis/weather.json
mfire/locale/en/synthesis/wind.json
mfire/locale/es/compass.json
mfire/locale/es/date.json
mfire/locale/es/period.csv
mfire/locale/es/synonyms.json
mfire/locale/es/wwmf_labels.csv
mfire/locale/es/LC_MESSAGES/mfire.mo
mfire/locale/es/risk/ME.json
mfire/locale/es/risk/monozone.csv
mfire/locale/es/risk/multizone.json
mfire/locale/es/risk/rain.json
mfire/locale/es/risk/rep_value.json
mfire/locale/es/risk/rep_value_altitude.json
mfire/locale/es/risk/rep_value_lpn.json
mfire/locale/es/risk/snow.json
mfire/locale/es/synthesis/nebulosity_following_labels.csv
mfire/locale/es/synthesis/temperature.json
mfire-4.2.post1.dist-info/licenses/LICENSE.md
mfire-4.2.post1.dist-info/METADATA
mfire-4.2.post1.dist-info/WHEEL
mfire-4.2.post1.dist-info/top_level.txt
mfire-4.2.post1.dist-info/RECORD
