Metadata-Version: 2.4
Name: mfire
Version: 4.2.post1
Summary: Code for PROMETHEE project
Home-page: https://git.meteo.fr/deep_learning/ftap_autom
Author: LabIA-MF
Author-email: lab_ia@meteo.fr
License: All rights reserved
Classifier: Programming Language :: Python :: 3
Classifier: Operating System :: OS Independent
License-File: LICENSE.md
Requires-Dist: bottleneck==1.3.8
Requires-Dist: cfgrib==0.9.11.0
Requires-Dist: geojson==3.1.0
Requires-Dist: jinja2==3.1.6
Requires-Dist: netcdf4==1.6.5
Requires-Dist: pandas==2.2.2
Requires-Dist: pint==0.23
Requires-Dist: pydantic==2.7.1
Requires-Dist: pydantic-settings==2.2.1
Requires-Dist: python-dateutil==2.9.0.post0
Requires-Dist: shapely==2.0.4
Requires-Dist: timezonefinder==6.5.7
Requires-Dist: xarray==2024.5.0
Requires-Dist: mflog==0.1.0
Requires-Dist: python-gettext==5.0
Provides-Extra: develop
Requires-Dist: bandit==1.8.3; extra == "develop"
Requires-Dist: black==25.1.0; extra == "develop"
Requires-Dist: flake8==7.2.0; extra == "develop"
Requires-Dist: pytest==8.2.1; extra == "develop"
Requires-Dist: pytest-cov==5.0.0; extra == "develop"
Requires-Dist: pytest-xdist==3.6.1; extra == "develop"
Requires-Dist: pylint==3.3.3; extra == "develop"
Requires-Dist: pydoclint==0.6.6; extra == "develop"
Dynamic: author
Dynamic: author-email
Dynamic: classifier
Dynamic: description
Dynamic: description-content-type
Dynamic: home-page
Dynamic: license
Dynamic: license-file
Dynamic: provides-extra
Dynamic: requires-dist
Dynamic: summary
